publisher/__init__.py
publisher/__main__.py
publisher/_version.py
publisher/copy.py
publisher/meta.json
publisher/meta.py
publisher/project.py
publisher/sample.py
publisher/setup_json.py
publisher/tool.py
publisher/utils.py
publisher/_samples/__init__.py
publisher/_samples/_sample_setup.py
publisher/_samples/_sample_version.py
publisher/_samples/_shim_setup.py
pipenv_publisher-0.1.0a7.post2.dist-info/LICENSE.md
pipenv_publisher-0.1.0a7.post2.dist-info/METADATA
pipenv_publisher-0.1.0a7.post2.dist-info/WHEEL
pipenv_publisher-0.1.0a7.post2.dist-info/entry_points.txt
pipenv_publisher-0.1.0a7.post2.dist-info/top_level.txt
pipenv_publisher-0.1.0a7.post2.dist-info/RECORD
