Metadata-Version: 2.1
Name: pipenv-publisher
Version: 0.1.0a7.post2
Summary: Pipenv integration for setuptools.
Home-page: UNKNOWN
Author: Krystian Postek
Author-email: krystian@postek.eu
License: Apache
Project-URL: Repository, https://github.com/kpostekk/pipenv-publisher
Platform: UNKNOWN
Classifier: Development Status :: 3 - Alpha
Classifier: Intended Audience :: Developers
Classifier: License :: OSI Approved :: Apache Software License
Requires-Dist: pipenv
Requires-Dist: ezcliy (>=0.2.1)
